__init__.py
precise_rounding.py
precise_rounding-0.1.2.dist-info/LICENSE
precise_rounding-0.1.2.dist-info/METADATA
precise_rounding-0.1.2.dist-info/WHEEL
precise_rounding-0.1.2.dist-info/top_level.txt
precise_rounding-0.1.2.dist-info/RECORD
